seedspark/__init__.py
seedspark/apps/__init__.py
seedspark/apps/clickhouse_delta.py
seedspark/configs/__init__.py
seedspark/configs/clickhouse.py
seedspark/configs/configs.py
seedspark/connections/__init__.py
seedspark/connections/clickhouse.py
seedspark/connections/clickhouse_dialect.py
seedspark/contrib/__init__.py
seedspark/contrib/testing/__init__.py
seedspark/contrib/testing/spark.py
seedspark/decorators.py
seedspark/examples/__init__.py
seedspark/examples/clichouse_taxi.py
seedspark/examples/music_sessions_explore.py
seedspark/examples/music_sessions_top_n.py
seedspark/examples/postgres.py
seedspark/examples/sql/weekend_trip_metrics.sql
seedspark/examples/weekend_fares_kpi.py
seedspark/examples/word_count.py
seedspark/sparkapp.py
seedspark-0.5.1.dist-info/METADATA
seedspark-0.5.1.dist-info/WHEEL
seedspark-0.5.1.dist-info/RECORD
