Metadata-Version: 2.1
Name: seedspark
Version: 0.5.1
Summary: Spark ETL Utility Framework
Author: ChethanUK
Author-email: chethanuk@outlook.com
Requires-Python: >=3.9,<4.0
Classifier: Programming Language :: Python :: 3
Classifier: Programming Language :: Python :: 3.9
Classifier: Programming Language :: Python :: 3.10
Classifier: Programming Language :: Python :: 3.11
Classifier: Programming Language :: Python :: 3.12
Requires-Dist: delta-spark (==3.1.0)
Requires-Dist: loguru (>=0.7.2,<0.8.0)
Requires-Dist: onetl (>=0.10.1,<0.11.0)
Requires-Dist: pyspark[connect,sql] (>=3.5.0,<4.0.0)
Requires-Dist: requests (>=2.31.0,<3.0.0)
Requires-Dist: sqlglot (>=20.11.0,<21.0.0)
